centralized_pre_commit_conf/__init__.py
centralized_pre_commit_conf/config_default.yaml
centralized_pre_commit_conf/constants.py
centralized_pre_commit_conf/download_configuration.py
centralized_pre_commit_conf/install.py
centralized_pre_commit_conf/main.py
centralized_pre_commit_conf/parse_args.py
centralized_pre_commit_conf/prints.py
centralized_pre_commit_conf/update_gitignore.py
tests/test_get_url_from_args.py
tests/test_integration.py
tests/test_update_gitignore.py
centralized_pre_commit_conf-0.6.1.dist-info/LICENSE
centralized_pre_commit_conf-0.6.1.dist-info/METADATA
centralized_pre_commit_conf-0.6.1.dist-info/WHEEL
centralized_pre_commit_conf-0.6.1.dist-info/entry_points.txt
centralized_pre_commit_conf-0.6.1.dist-info/top_level.txt
centralized_pre_commit_conf-0.6.1.dist-info/zip-safe
centralized_pre_commit_conf-0.6.1.dist-info/RECORD
