Metadata-Version: 2.1
Name: centralized-pre-commit-conf
Version: 0.6.1
Summary: Easily install and update centralized pre-commit hooks and their configuration files in decentralized repositories
Home-page: https://github.com/Pierre-Sassoulas/centralized-pre-commit-conf
Author: Pierre Sassoulas
Author-email: pierre.sassoulas@gmail.com
Classifier: Operating System :: OS Independent
Classifier: Intended Audience :: Developers
Classifier: License :: OSI Approved :: MIT License
Classifier: Programming Language :: Python :: 3.7
Classifier: Programming Language :: Python :: 3.8
Classifier: Programming Language :: Python :: 3.9
Classifier: Programming Language :: Python :: 3.10
Classifier: Programming Language :: Python :: 3.11
Classifier: Development Status :: 5 - Production/Stable
License-File: LICENSE
Requires-Dist: setuptools (>=45.1)
Requires-Dist: wheel (>=0.34)
Requires-Dist: colorama
Requires-Dist: confuse
Requires-Dist: pre-commit (>=1.16)
Requires-Dist: requests
Provides-Extra: test
Requires-Dist: pytest-cov ; extra == 'test'
Requires-Dist: pytest-vcr ; extra == 'test'
Requires-Dist: coverage ; extra == 'test'
Requires-Dist: python-coveralls ; extra == 'test'
Requires-Dist: coveralls ; extra == 'test'
Requires-Dist: pylint (==2.15.4) ; extra == 'test'
